cdk_serverless_lamp/__init__.py
cdk_serverless_lamp/py.typed
cdk_serverless_lamp/_jsii/__init__.py
cdk_serverless_lamp/_jsii/cdk-serverless-lamp@1.4.54.jsii.tgz
cdk_serverless_lamp-1.4.54.data/scripts/jsii-release-npm
cdk_serverless_lamp-1.4.54.dist-info/LICENSE
cdk_serverless_lamp-1.4.54.dist-info/METADATA
cdk_serverless_lamp-1.4.54.dist-info/NOTICE
cdk_serverless_lamp-1.4.54.dist-info/WHEEL
cdk_serverless_lamp-1.4.54.dist-info/top_level.txt
cdk_serverless_lamp-1.4.54.dist-info/RECORD
