Metadata-Version: 2.1
Name: cdk-serverless-lamp
Version: 1.4.54
Summary: A JSII construct lib to build AWS Serverless LAMP with AWS CDK
Home-page: https://github.com/aws-samples/cdk-serverless-lamp.git
Author: Pahud Hsieh<hunhsieh@amazon.com>
License: Apache-2.0
Project-URL: Source, https://github.com/aws-samples/cdk-serverless-lamp.git
Platform: UNKNOWN
Classifier: Intended Audience :: Developers
Classifier: Operating System :: OS Independent
Classifier: Programming Language :: JavaScript
Classifier: Programming Language :: Python :: 3 :: Only
Classifier: Programming Language :: Python :: 3.6
Classifier: Programming Language :: Python :: 3.7
Classifier: Programming Language :: Python :: 3.8
Classifier: Programming Language :: Python :: 3.9
Classifier: Typing :: Typed
Classifier: Development Status :: 5 - Production/Stable
Classifier: License :: OSI Approved
Requires-Python: >=3.6
License-File: LICENSE
License-File: NOTICE
Requires-Dist: aws-cdk-lib (<3.0.0,>=2.18.0)
Requires-Dist: aws-cdk.aws-apigatewayv2-alpha (<3.0.0,>=2.18.0.a0)
Requires-Dist: aws-cdk.aws-apigatewayv2-integrations-alpha (<3.0.0,>=2.18.0.a0)
Requires-Dist: constructs (<11.0.0,>=10.0.5)
Requires-Dist: jsii (<2.0.0,>=1.55.1)
Requires-Dist: publication (>=0.0.3)
